geekbot_api/__init__.py
geekbot_api/client.py
geekbot_api/clients/__init__.py
geekbot_api/clients/reports.py
geekbot_api/clients/standups.py
geekbot_api/clients/teams.py
geekbot_api/config.py
geekbot_api/py.typed
geekbot_api/schemas.py
geekbot_api-0.2.1.dist-info/LICENSE
geekbot_api-0.2.1.dist-info/WHEEL
geekbot_api-0.2.1.dist-info/METADATA
geekbot_api-0.2.1.dist-info/RECORD
