Metadata-Version: 2.1
Name: geekbot-api
Version: 0.2.1
Summary: Async Python client for the geekbot (https://geekbot.com) api
Home-page: https://github.com/andrewthetechie/geekbot-api-py
License: MIT
Author: Andrew Herrington
Author-email: andrew.the.techie@gmail.com
Requires-Python: >=3.7,<4.0
Classifier: Development Status :: 4 - Beta
Classifier: License :: OSI Approved :: MIT License
Classifier: Programming Language :: Python :: 3
Classifier: Programming Language :: Python :: 3.7
Classifier: Programming Language :: Python :: 3.8
Classifier: Programming Language :: Python :: 3.9
Classifier: Programming Language :: Python :: 3.10
Classifier: Programming Language :: Python :: 3.11
Requires-Dist: httpx (>=0.23.3,<0.24.0)
Requires-Dist: pydantic (>=1.10.5,<2.0.0)
Requires-Dist: requests (>=2.28.2,<3.0.0)
Project-URL: Changelog, https://github.com/andrewthetechie/geekbot-api-py/releases
Project-URL: Repository, https://github.com/andrewthetechie/geekbot-api-py
